Raunak_STT/__init__.py
automate_vcr-1.0.0.dist-info/METADATA
automate_vcr-1.0.0.dist-info/WHEEL
automate_vcr-1.0.0.dist-info/top_level.txt
automate_vcr-1.0.0.dist-info/RECORD
