Metadata-Version: 2.4
Name: Automate-VCR
Version: 1.0.0
Summary: Automate VCR by Raunak Raj
Author: Raunak Raj
Author-email: test@gmail.com
Requires-Python: >=3.8
Requires-Dist: selenium
Requires-Dist: webdriver-manager
Dynamic: author
Dynamic: author-email
Dynamic: requires-dist
Dynamic: requires-python
Dynamic: summary
